{
  "categories": [
    {
      "id": "all",
      "name": "All",
      "count": 12
    },
    {
      "id": "wedding",
      "name": "Wedding",
      "count": 4,
      "cover": "https://images.pexels.com/photos/169198/pexels-photo-169198.jpeg?auto=compress&cs=tinysrgb&w=800"
    },
    {
      "id": "portrait",
      "name": "Portrait",
      "count": 4,
      "cover": "https://images.pexels.com/photos/614810/pexels-photo-614810.jpeg?auto=compress&cs=tinysrgb&w=800"
    },
    {
      "id": "nature",
      "name": "Nature",
      "count": 4,
      "cover": "https://images.pexels.com/photos/3225517/pexels-photo-3225517.jpeg?auto=compress&cs=tinysrgb&w=800"
    }
      "id": "event",
      "name": "Event",
      "count": 5,
      "cover": "/gallery/event/1.jpg"
    },
    {
      "id": "lifestyle",
      "name": "Lifestyle",
      "count": 4,
      "cover": "/gallery/lifestyle/1.jpg"
    },
    {
      "id": "corporate",
      "name": "Corporate",
      "count": 3,
      "cover": "/gallery/corporate/1.jpg"
    },
    {
      "id": "family",
      "name": "Family",
      "count": 2,
      "cover": "/gallery/family/1.jpg"
    }
  ],
  "images": [
    {
      "id": 1,
      "src": "https://images.pexels.com/photos/169198/pexels-photo-169198.jpeg?auto=compress&cs=tinysrgb&w=800",
      "category": "wedding",
      "alt": "Wedding couple at sunset",
      "title": "Sunset Vows",
      "description": "Beautiful couple exchanging vows during golden hour"
    },
    {
      "id": 2,
      "src": "/gallery/wedding/2.jpg",
      "category": "wedding",
      "alt": "Bride preparing for ceremony",
      "title": "Bride's Preparation",
      "description": "Candid moments of the bride getting ready"
    },
    {
      "id": 3,
      "src": "/gallery/wedding/3.jpg",
      "category": "wedding",
      "alt": "First dance",
      "title": "First Dance",
      "description": "The couple's magical first dance as husband and wife"
    },
    {
      "id": 4,
      "src": "/gallery/portrait/1.jpg",
      "category": "portrait",
      "alt": "Professional headshot",
      "title": "Corporate Portrait",
      "description": "Professional headshot for corporate profile"
    },
    {
      "id": 5,
      "src": "/gallery/portrait/2.jpg",
      "category": "portrait",
      "alt": "Creative portrait",
      "title": "Creative Portrait",
      "description": "Artistic portrait with creative lighting"
    },
    {
      "id": 6,
      "src": "/gallery/event/1.jpg",
      "category": "event",
      "alt": "Concert photography",
      "title": "Live Performance",
      "description": "Capturing the energy of a live music event"
    },
    {
      "id": 7,
      "src": "/gallery/lifestyle/1.jpg",
      "category": "lifestyle",
      "alt": "Lifestyle portrait",
      "title": "Urban Lifestyle",
      "description": "Casual lifestyle portrait in the city"
    },
    {
      "id": 8,
      "src": "/gallery/corporate/1.jpg",
      "category": "corporate",
      "alt": "Corporate event",
      "title": "Business Conference",
      "description": "Professional coverage of a corporate conference"
    },
    {
      "id": 9,
      "src": "/gallery/family/1.jpg",
      "category": "family",
      "alt": "Family portrait",
      "title": "Family Portrait",
      "description": "Beautiful family moments captured outdoors"
    },
    {
      "id": 10,
      "src": "/gallery/wedding/4.jpg",
      "category": "wedding",
      "alt": "Wedding details",
      "title": "Wedding Details",
      "description": "Elegant details from a beautiful wedding"
    },
    {
      "id": 11,
      "src": "/gallery/portrait/3.jpg",
      "category": "portrait",
      "alt": "Black and white portrait",
      "title": "Monochrome",
      "description": "Dramatic black and white portrait"
    },
    {
      "id": 12,
      "src": "/gallery/event/2.jpg",
      "category": "event",
      "alt": "Birthday celebration",
      "title": "Birthday Bash",
      "description": "Joyful moments from a birthday celebration"
    },
    {
      "id": 13,
      "src": "/gallery/wedding/5.jpg",
      "category": "wedding",
      "alt": "Bridal party",
      "title": "Bridal Party",
      "description": "The happy couple with their wedding party"
    },
    {
      "id": 14,
      "src": "/gallery/portrait/4.jpg",
      "category": "portrait",
      "alt": "Environmental portrait",
      "title": "Environmental Portrait",
      "description": "Portrait in natural surroundings"
    },
    {
      "id": 15,
      "src": "/gallery/event/3.jpg",
      "category": "event",
      "alt": "Corporate gala",
      "title": "Gala Night",
      "description": "Elegant evening at a corporate gala"
    },
    {
      "id": 16,
      "src": "/gallery/lifestyle/2.jpg",
      "category": "lifestyle",
      "alt": "Travel lifestyle",
      "title": "Wanderlust",
      "description": "Travel and adventure lifestyle photography"
    },
    {
      "id": 17,
      "src": "/gallery/corporate/2.jpg",
      "category": "corporate",
      "alt": "Office lifestyle",
      "title": "Workplace",
      "description": "Professional workplace photography"
    },
    {
      "id": 18,
      "src": "/gallery/wedding/6.jpg",
      "category": "wedding",
      "alt": "Wedding ceremony",
      "title": "I Do",
      "description": "Emotional moment during the wedding ceremony"
    },
    {
      "id": 19,
      "src": "/gallery/portrait/5.jpg",
      "category": "portrait",
      "alt": "Fashion portrait",
      "title": "Fashion Forward",
      "description": "Stylish fashion portrait session"
    },
    {
      "id": 20,
      "src": "/gallery/event/4.jpg",
      "category": "event",
      "alt": "Product launch",
      "title": "Product Launch",
      "description": "Coverage of an exclusive product launch event"
    },
    {
      "id": 21,
      "src": "/gallery/lifestyle/3.jpg",
      "category": "lifestyle",
      "alt": "Fitness lifestyle",
      "title": "Active Living",
      "description": "Energetic fitness lifestyle photography"
    },
    {
      "id": 22,
      "src": "https://images.pexels.com/photos/3225517/pexels-photo-3225517.jpeg?auto=compress&cs=tinysrgb&w=800",
      "category": "wedding",
      "alt": "Wedding photo 1",
      "description": "Celebratory moments from the wedding reception"
    },
    {
      "id": 23,
      "src": "/gallery/portrait/6.jpg",
      "category": "portrait",
      "alt": "Maternity portrait",
      "title": "Motherhood",
      "description": "Touching maternity portrait session"
    },
    {
      "id": 24,
      "src": "/gallery/event/5.jpg",
      "category": "event",
      "alt": "Award ceremony",
      "title": "Achievement",
      "description": "Special moments from an award ceremony"
    },
    {
      "id": 25,
      "src": "/gallery/corporate/3.jpg",
      "category": "corporate",
      "alt": "Team photo",
      "title": "Team Spirit",
      "description": "Professional team photography"
    },
    {
      "id": 26,
      "src": "/gallery/lifestyle/4.jpg",
      "category": "lifestyle",
      "alt": "Culinary lifestyle",
      "title": "Culinary Arts",
      "description": "Beautiful food and culinary lifestyle"
    },
    {
      "id": 27,
      "src": "/gallery/wedding/8.jpg",
      "category": "wedding",
      "alt": "Wedding exit",
      "title": "Just Married",
      "description": "Joyful exit as newlyweds"
    },
    {
      "id": 28,
      "src": "/gallery/family/2.jpg",
      "category": "family",
      "alt": "Newborn family",
      "title": "New Beginnings",
      "description": "Precious moments with a newborn"
    }
  ]
}
